{"XOSh4UrfotRcIeYc2efQSQ==":"moon-cannon-potato-gun.jpg","ve2bCa2Bll9mnzsRPeSWsw==":"prod-image-250x250.jpg","mctKrhdknYjHk1O6S6LjkQ==":"0c8e12751d87cd3aee839f917737504f.jpg","JmEbc5FsQTsl73tVLp5swA==":"prod-image-1-250x250.jpg","VUEk/KkpPbLllEEq04SSYQ==":"candle-making-473x299.jpg","EMhUHSJXVF61GyGIs+cbRA==":"moon-cannon-potato-gun-506x422.jpg","vlpx5He3DXZ+31Q1BDmzVQ==":"maxresdefault_potato+cannon-506x285.jpg","pstn/qPb022blNP/47zP+A==":"0c8e12751d87cd3aee839f917737504f-506x637.jpg","d4ovoVpDD9aer3aGTo7l9g==":"maxresdefault-506x285.jpg","QwGd8EORRBsviUctHAwjaA==":"2e6b0a5dd16e56ac4856d85f2e6060a4-506x380.jpg","ZAknfS0PVQgt1fZm9pyj3w==":"img_f2e7c3840b7fb1f0b8d663f4a0bbfa9c_1556448030226_processed_original-506x298.jpg","7pS4lsMYkxIk6PmrVvzcbw==":"front_page-500x402.jpg","f1AKpcFLiFqny1kjlx5PMw==":"unnamed-320x242.jpg","xPufrcpF0Hn9NHa9G4ffEw==":"unnamed%20(1)-506x422.jpg","9aGNJAKnzaufhYk6QzkLsg==":"diy-how-to-make-crayon-watermelon-candles-17-506x305.jpg","apx0kGLMsfysSvc50+LlSg==":"10-minute-gift-idea-diy-citrus-fresh-soy-candles-506x759.jpg","jip1mbFum2EG1QRPO9R2OA==":"10-minute-gift-idea-diy-citrus-fresh-soy-candles-506x759.jpeg","Ysp0dMbkgBU48AWcTXON3g==":"10-minute-gift-idea-diy-citrus-fresh-soy-candles-1-506x759.jpeg","x7gHV8FC4XaAQe5P+l70Lw==":"10-minute-gift-idea-diy-citrus-fresh-soy-candles-2-506x759.jpeg","tXmtPdqCRBbugaZ3i+juyA==":"f15c4d5733d979552d051148f7739c7d-506x217.jpg","m8iq0GxuKnr3cM3LDvVdkQ==":"different-candle-wicks-500x335.jpg","zTzjQEKDiKoYFlsoMweDzw==":"ffc2aef6808895b015c259881a547db3-506x632.jpg","uMSExieqJfTV8S96EoDqRQ==":"maxresdefault%20(1)-506x285.jpeg","UZaQXnfFacvC0F2HhnR4oQ==":"ffc2aef6808895b015c259881a547db3-506x632.jpeg","oy3CVkyrLjbbo/lxdu6UFA==":"different-candle-wicks-500x335.jpeg","WcXbhbZloa981dqsHS5GRw==":"f15c4d5733d979552d051148f7739c7d-506x217.jpeg","XKRrn4+tl7CtcBZCbQhwFA==":"10-minute-gift-idea-diy-citrus-fresh-soy-candles-3-506x759.jpeg","L08Ir4oHArLrw2qGqfLvXA==":"diy-how-to-make-crayon-watermelon-candles-17-506x305.jpeg","2+YahJLygqnPuB5q/iqghA==":"unnamed%20(1)-506x422.jpeg","+XLbFoNwC+WdQkl6MYIFAg==":"maxresdefault%20(1)-506x285.jpeg","X6wFiEuAJv80rY1TfQTTTQ==":"2e6b0a5dd16e56ac4856d85f2e6060a4-506x380.jpeg","EdORcv13iBIeQBP9zzwfLg==":"maxresdefault-506x285.jpeg","wuGUHYcqgNl81M83bVL09Q==":"unnamed-320x242.jpeg","h/9PQfhXRCDP6jsXKAFo1Q==":"front_page-500x402.jpeg","Nvah+34SRbk7zq4SO/CEOA==":"maxresdefault_potato+cannon-506x285.jpeg","5FLZp1BGMi3jRF4ctVklDw==":"moon-cannon-potato-gun-506x422.jpeg","5Veivl3BZohLr65NvPGhsQ==":"candle-making-473x299.jpeg","EG8lIa6oMZlDqFGbtDierg==":"candle-making-1-473x299.jpeg","1+xZd/yxN2xjwVW011PFFA==":"moon-cannon-potato-gun.jpeg","AAogQKgwrgqOVHYVrPgN6Q==":"prod-image-250x250.jpeg","lXuRQzZpAsYBvfnrEbP5Ng==":"2e6b0a5dd16e56ac4856d85f2e6060a4-1-506x380.jpeg","8zewmyrlWYn60tmgeS9xxw==":"maxresdefault%20(1)-506x285.jpeg","DAAm3C1tFzMzcuqXw7kVYg==":"unnamed%20(1)-506x422.jpeg","oqF5yglEtnRVYkU28cbaYw==":"diy-how-to-make-crayon-watermelon-candles-18-506x305.jpeg","biltAYepEeM8QhVOFvBIhQ==":"10-minute-gift-idea-diy-citrus-fresh-soy-candles-4-506x759.jpeg","XpbgzUFEs/VnnOXBkzlVLw==":"maxresdefault-1-506x285.jpeg","gvettP7rDc30gJ6YwBEl7Q==":"maxresdefault-2-506x285.jpeg","D6wvBa/5vG4lHWEae/g3cA==":"pink%20teal%20photo%20birthday%20events%20website%20(5)-1350x650.png","sCRopPhxqDycgtKb4jZvLg==":"10-minute-gift-idea-diy-citrus-fresh-soy-candles-5-506x759.jpeg","8bZNJpP0ikrdsX5AIk+aXA==":"img_20201110_130800-removebg-preview-455x548.png","/h0L6CEYcByJn1jkqkcVBA==":"img_20201110_130800-removebg-preview-1-455x548.png","/jvZKLj+rwR+ARbIChSa/w==":"whatsapp_image_2020-11-09_at_10.54.48_am-removebg-preview-375x666.png","SAlpAv6hcI7EAotAhQen/A==":"img_20201103_180004-removebg-preview%20(1)-506x380.png","TiKiPuibOkVl/H3sO52ZkA==":"snapchat-1997828069-506x900.jpeg","6xw9nDJxUPZrIJURdujHww==":"img_20201110-151352-1076x1312.jpeg","RSuZyL8lxn+Kjq1Zw1Ho/Q==":"img_20201103-184452-452x588.jpeg","ytqLqGqqc0DYOSVx9g6xJg==":"img_20201110-151353-1076x1312.jpeg","76Z0zmE1Q8VzHMFhPXJYYQ==":"img_20201103-184453-452x588.jpeg","5Gy0BxtNDH4hmqkSmFodVg==":"img_20201110-151352-506x617.jpeg","fQbWowvItoaKc3pMYv4nzQ==":"moon-cannon-potato-gun-1-506x422.jpeg","89Gl3jpdXINu3xNBtdoxMg==":"front_page-1-500x402.jpeg"}